{
  "stage": 1,
  "retry_count": 0,
  "mechanic": {
    "mechanic_name": "threshold_sabotage_reflection",
    "mechanic_type": "scoring",
    "description": "If a player plays a card whose value would bring their score to exactly 19, the opponent loses 1 point immediately (if they have at least 1).",
    "python_code": "import numpy as np\n\ndef threshold_sabotage_reflection(game_state: dict) -> dict:\n    # Ensure custom_state exists\n    cs = game_state.setdefault('custom_state', {})\n\n    # Read required fields\n    current_player = game_state.get('current_player', 1)\n    other_player = 2 if current_player == 1 else 1\n    scores = game_state.setdefault('scores', {1: 0, 2: 0})\n\n    # Determine which card was just played\n    last_played = game_state.get('last_played', None)\n    if last_played is None:\n        return game_state\n\n    # Apply sabotage only on exact-19 reaching play by current player\n    cur_score = scores.get(current_player, 0)\n    if cur_score + last_played == 19:\n        opp_score = scores.get(other_player, 0)\n        if opp_score >= 1:\n            scores[other_player] = opp_score - 1\n\n    return game_state\n",
    "justification": "This adds a clear, tactical breakpoint players can aim for or avoid, improving decision-making without guaranteeing a win for either side.",
    "hook_location": "perform_move"
  },
  "integration": {
    "schema_ok": true,
    "syntax_ok": true,
    "hook_ok": true,
    "instantiation_ok": true,
    "dry_run_ok": true,
    "error_message": ""
  },
  "parent_metrics": {
    "total_matches": 16,
    "completed_matches": 16,
    "p1_wins": 7,
    "p2_wins": 9,
    "draws": 0,
    "p1_win_rate": 0.438,
    "p2_win_rate": 0.562,
    "balance_gap": 0.125,
    "draw_rate": 0.0,
    "decisiveness": 1.0,
    "avg_game_length": 5.562,
    "multi_choice_turns": 88,
    "total_turns": 89,
    "agency": 0.989,
    "covered_cells": 6,
    "board_cell_count": 10,
    "coverage": 0.556,
    "strong_vs_weak_matches": 16,
    "strong_agent_wins": 14,
    "weak_agent_wins": 1,
    "strong_agent_win_rate": 0.875,
    "weak_agent_win_rate": 0.062,
    "depth": 0.812
  },
  "child_metrics": {
    "total_matches": 16,
    "completed_matches": 16,
    "p1_wins": 9,
    "p2_wins": 5,
    "draws": 2,
    "p1_win_rate": 0.562,
    "p2_win_rate": 0.312,
    "balance_gap": 0.25,
    "draw_rate": 0.125,
    "decisiveness": 0.875,
    "avg_game_length": 6.688,
    "multi_choice_turns": 100,
    "total_turns": 107,
    "agency": 0.935,
    "covered_cells": 7,
    "board_cell_count": 10,
    "coverage": 0.669,
    "strong_vs_weak_matches": 16,
    "strong_agent_wins": 12,
    "weak_agent_wins": 1,
    "strong_agent_win_rate": 0.75,
    "weak_agent_win_rate": 0.062,
    "depth": 0.688
  },
  "trigger_stats": {
    "trigger_count": 107,
    "triggered_matches": 16,
    "total_matches": 16,
    "total_turns": 107,
    "state_changed_by_mechanic_count": 6,
    "trigger_rate_by_match": 1.0,
    "trigger_rate_by_turn": 1.0
  },
  "derived_scores": {
    "playability": 1.0,
    "balance_gap": 0.25,
    "depth": 0.688,
    "aggregate": 0.719
  },
  "parent_summary": "Baseline game without the new mechanic."
}